t2i/__init__.py
t2i/decorators.py
t2i/tests/__init__.py
t2i/tests/t2i_test.py
token2index-1.0.2.dist-info/LICENSE
token2index-1.0.2.dist-info/METADATA
token2index-1.0.2.dist-info/WHEEL
token2index-1.0.2.dist-info/top_level.txt
token2index-1.0.2.dist-info/RECORD
