Metadata-Version: 2.1
Name: token2index
Version: 1.0.2
Summary: A lightweight but powerful library for token indexing.
Home-page: https://github.com/Kaleidophon/token2index
Author: Dennis Ulmer
License: GPL
Keywords: indexing,token,nlp,pytorch,tensorflow,numpy,w2i,t2i,stoi,itos,i2t,i2w,deep learning,seq2seq
Platform: UNKNOWN
Classifier: Intended Audience :: Science/Research
Classifier: Topic :: Scientific/Engineering :: Artificial Intelligence
Classifier: Programming Language :: Python :: 3
Classifier: License :: OSI Approved :: GNU General Public License v3 or later (GPLv3+)
Classifier: Operating System :: OS Independent
Requires-Python: >=3.5.3
